madsci/resource_manager/__init__.py
madsci/resource_manager/alembic.ini
madsci/resource_manager/alembic/README
madsci/resource_manager/alembic/env.py
madsci/resource_manager/alembic/script.py.mako
madsci/resource_manager/database_version_checker.py
madsci/resource_manager/migration_tool.py
madsci/resource_manager/resource_interface.py
madsci/resource_manager/resource_server.py
madsci/resource_manager/resource_tables.py
madsci_resource_manager-0.6.1.dist-info/METADATA
madsci_resource_manager-0.6.1.dist-info/WHEEL
madsci_resource_manager-0.6.1.dist-info/entry_points.txt
madsci_resource_manager-0.6.1.dist-info/RECORD
